tinyxmpp/__init__.py
tinyxmpp-0.1.1.dist-info/LICENSE
tinyxmpp-0.1.1.dist-info/METADATA
tinyxmpp-0.1.1.dist-info/WHEEL
tinyxmpp-0.1.1.dist-info/top_level.txt
tinyxmpp-0.1.1.dist-info/RECORD
