Metadata-Version: 2.1
Name: tinyxmpp
Version: 0.1.1
Summary: A friendly and easy to use XMPP client for Python
Home-page: https://github.com/stan-janssen/tinyxmpp
Author: Stan Janssen
License: UNKNOWN
Platform: UNKNOWN
Requires-Dist: lxml
Requires-Dist: tinysasl
